arxiv_agent/__init__.py
arxiv_agent/graphs/__init__.py
arxiv_agent/graphs/agent_v1.py
arxiv_agent/graphs/agent_v2.py
arxiv_agent/graphs/agent_v5.py
arxiv_agent/graphs/agent_v6.py
arxiv_agent/graphs/agent_v7.py
arxiv_agent/graphs/agent_v72.py
arxiv_agent/graphs/agent_v8.py
arxiv_agent/graphs/agent_v82.py
arxiv_agent/graphs/agent_v9.py
arxiv_agent/graphs/test_memento.py
arxiv_agent/graphs/agent_v4/__init__.py
arxiv_agent/graphs/agent_v4/agent.py
arxiv_agent/graphs/agent_v4/instructions.py
arxiv_agent/graphs/agent_v4/predict4.py
arxiv_agent/graphs/agent_v4/predict4_albert.py
arxiv_agent/graphs/agent_v4/prompt_templates.py
arxiv_agent/graphs/agent_v4/utils.py
arxiv_agent/nodes/__init__.py
arxiv_agent/nodes/actor.py
arxiv_agent/nodes/actor_history.py
arxiv_agent/nodes/actor_history_1.py
arxiv_agent/nodes/api.py
arxiv_agent/nodes/base.py
arxiv_agent/nodes/expert.py
arxiv_agent/nodes/hotpot_actor.py
arxiv_agent/nodes/qa_agent_history.py
arxiv_agent/nodes/summarizer.py
arxiv_agent/nodes/terminator.py
arxiv_agent/prompts/__init__.py
arxiv_agent/prompts/hotpot_few_shot.py
arxiv_agent/schemas/__init__.py
arxiv_agent/schemas/hotpot.py
arxiv_agent/schemas/notes.py
arxiv_agent/schemas/qasper.py
arxiv_agent/toolkits/__init__.py
arxiv_agent/toolkits/arxiv.py
arxiv_agent/toolkits/sql.py
arxiv_agent/toolkits/wiki.py
arxiv_agent/tools/__init__.py
arxiv_agent/tools/misc_tool.py
arxiv_agent/tools/paper/__init__.py
arxiv_agent/tools/paper/bibitem_tool.py
arxiv_agent/tools/paper/figures_tool.py
arxiv_agent/tools/paper/lookup_tool.py
arxiv_agent/tools/paper/navigation_tool.py
arxiv_agent/tools/paper/section_tool.py
arxiv_agent/tools/paper/summary_tool.py
arxiv_agent/tools/paper/tables_tool.py
arxiv_agent/tools/paper/utils.py
arxiv_agent/tools/s2/SemanticScholarAPIWrapper.py
arxiv_agent/tools/s2/SemanticScholarQueryRun.py
arxiv_agent/tools/s2/__init__.py
arxiv_agent/tools/search/__init__.py
arxiv_agent/tools/search/arxiv_categories.py
arxiv_agent/tools/search/tool.py
arxiv_agent-0.0.0.dist-info/METADATA
arxiv_agent-0.0.0.dist-info/WHEEL
arxiv_agent-0.0.0.dist-info/top_level.txt
arxiv_agent-0.0.0.dist-info/RECORD
