Metadata-Version: 2.1
Name: arxiv_agent
Version: 0.0.0
Summary: LLM agent to answer questions about arXiv papers
Requires-Dist: numpy
Requires-Dist: langchain
Requires-Dist: langgraph
Requires-Dist: langchain-openai
Requires-Dist: langchain-community
Requires-Dist: termcolor
Requires-Dist: bs4
Requires-Dist: arxiv
Requires-Dist: semanticscholar
